README.md
setup.cfg
setup.py
admin_service/__init__.py
admin_service/admin.py
admin_service/functions.py
admin_service/version.py
flint_admin_service.egg-info/PKG-INFO
flint_admin_service.egg-info/SOURCES.txt
flint_admin_service.egg-info/dependency_links.txt
flint_admin_service.egg-info/requires.txt
flint_admin_service.egg-info/top_level.txt